{
  "$schema": "https://json-schema.org/draft/2020-12/schema",
  "$comment": "generated by the ocm schema generation tool",
  "$id": "ocm.software/open-component-model/bindings/go/oci/spec/transformation/v1alpha1/schemas/OCIGetOCIArtifactSpec.schema.json",
  "title": "OCIGetOCIArtifactSpec",
  "type": "object",
  "description": "OCIGetOCIArtifactSpec is the input specification for the\nOCIGetOCIArtifact transformation.",
  "properties": {
    "outputPath": {
      "type": "string",
      "description": "OutputPath is the path where the artifact should be buffered.\nIf empty, a temporary file will be created."
    },
    "resourceIdentity": {
      "$ref": "#/$defs/ocm.software.open-component-model.bindings.go.runtime.Identity",
      "description": "ResourceIdentity identifies the resource to retrieve.\nMust match a resource in the component descriptor."
    }
  },
  "required": [
    "resourceIdentity"
  ],
  "additionalProperties": false,
  "$defs": {
    "ocm.software.open-component-model.bindings.go.runtime.Identity": {
      "$schema": "https://json-schema.org/draft/2020-12/schema",
      "$comment": "generated by the ocm schema generation tool",
      "title": "Identity",
      "type": "object",
      "description": "Identity is a map that represents a set of attributes that uniquely identity\narbitrary resources. It is used in various places in Open Component Model to uniquely\nidentity objects such as resources or components.",
      "additionalProperties": {
        "type": "string"
      }
    }
  }
}